QuizGenerator/__init__.py
QuizGenerator/__main__.py
QuizGenerator/constants.py
QuizGenerator/contentast.py
QuizGenerator/generate.py
QuizGenerator/misc.py
QuizGenerator/mixins.py
QuizGenerator/performance.py
QuizGenerator/qrcode_generator.py
QuizGenerator/question.py
QuizGenerator/quiz.py
QuizGenerator/regenerate.py
QuizGenerator/typst_utils.py
QuizGenerator/canvas/__init__.py
QuizGenerator/canvas/canvas_interface.py
QuizGenerator/canvas/classes.py
QuizGenerator/premade_questions/__init__.py
QuizGenerator/premade_questions/basic.py
QuizGenerator/premade_questions/cst334/__init__.py
QuizGenerator/premade_questions/cst334/languages.py
QuizGenerator/premade_questions/cst334/math_questions.py
QuizGenerator/premade_questions/cst334/memory_questions.py
QuizGenerator/premade_questions/cst334/ostep13_vsfs.py
QuizGenerator/premade_questions/cst334/persistence_questions.py
QuizGenerator/premade_questions/cst334/process.py
QuizGenerator/premade_questions/cst463/__init__.py
QuizGenerator/premade_questions/cst463/gradient_descent/__init__.py
QuizGenerator/premade_questions/cst463/gradient_descent/gradient_calculation.py
QuizGenerator/premade_questions/cst463/gradient_descent/gradient_descent_questions.py
QuizGenerator/premade_questions/cst463/gradient_descent/loss_calculations.py
QuizGenerator/premade_questions/cst463/gradient_descent/misc.py
QuizGenerator/premade_questions/cst463/math_and_data/__init__.py
QuizGenerator/premade_questions/cst463/math_and_data/matrix_questions.py
QuizGenerator/premade_questions/cst463/math_and_data/vector_questions.py
QuizGenerator/premade_questions/cst463/models/__init__.py
QuizGenerator/premade_questions/cst463/models/attention.py
QuizGenerator/premade_questions/cst463/models/cnns.py
QuizGenerator/premade_questions/cst463/models/matrices.py
QuizGenerator/premade_questions/cst463/models/rnns.py
QuizGenerator/premade_questions/cst463/models/text.py
QuizGenerator/premade_questions/cst463/models/weight_counting.py
quizgenerator-0.7.1.dist-info/METADATA
quizgenerator-0.7.1.dist-info/WHEEL
quizgenerator-0.7.1.dist-info/entry_points.txt
quizgenerator-0.7.1.dist-info/licenses/LICENSE
quizgenerator-0.7.1.dist-info/RECORD
