Metadata-Version: 2.4
Name: QuizGenerator
Version: 0.7.1
Summary: Generate randomized quiz questions for Canvas LMS and PDF exams
Project-URL: Homepage, https://github.com/OtterDen-Lab/QuizGenerator
Project-URL: Documentation, https://github.com/OtterDen-Lab/QuizGenerator/tree/main/documentation
Project-URL: Repository, https://github.com/OtterDen-Lab/QuizGenerator
Project-URL: Bug Tracker, https://github.com/OtterDen-Lab/QuizGenerator/issues
Author-email: Sam Ogden <samuel.s.ogden@gmail.com>
License: GPL-3.0-or-later
License-File: LICENSE
Keywords: assessment,canvas,education,exam,lms,quiz,teaching,testing
Classifier: Development Status :: 4 - Beta
Classifier: Intended Audience :: Education
Classifier: License :: OSI Approved :: GNU General Public License v3 or later (GPLv3+)
Classifier: Programming Language :: Python :: 3
Classifier: Programming Language :: Python :: 3.12
Classifier: Topic :: Education :: Testing
Requires-Python: >=3.12
Requires-Dist: canvasapi==3.2.0
Requires-Dist: cryptography>=41.0.0
Requires-Dist: graphviz>=0.21
Requires-Dist: jinja2==3.1.3
Requires-Dist: keras>=3.12.0
Requires-Dist: markdown>=3.9
Requires-Dist: matplotlib
Requires-Dist: pylatex>=1.4.2
Requires-Dist: pypandoc~=1.6.3
Requires-Dist: pytablewriter~=1.2.0
Requires-Dist: python-dotenv==1.0.1
Requires-Dist: pyyaml==6.0.1
Requires-Dist: requests==2.32.2
Requires-Dist: segno>=1.6.0
Requires-Dist: sympy>=1.14.0
Requires-Dist: tensorflow>=2.20.0
Provides-Extra: grading
Requires-Dist: pillow>=10.0.0; extra == 'grading'
Requires-Dist: pyzbar>=0.1.9; extra == 'grading'
